<VIPSPage PageRectHeight="600" PageRectLeft="0" PageRectTop="0" PageRectWidth="1200" PageTitle="&#10;      Sell Products Online with Google Shopping Campaigns – Google Shopping Campaigns&#10;    " Url="https://www.google.co.kr/intl/ko/retail/shopping-campaigns/" WindowHeight="600" WindowWidth="1200" neworder="0" order="0">
<LayoutNode BgColor="#ffffff" ContainImg="22" ContainP="7" ContainTable="false" DOMCldNum="3" DoC="1" FontSize="20" FontWeight="normal" FrameSourceIndex="0" ID="1" IsImg="false" LinkTextLen="442" ObjectRectHeight="5852" ObjectRectLeft="0" ObjectRectTop="0" ObjectRectWidth="1200" SourceIndex="118" TextLen="1543" order="1">
<LayoutNode BgColor="#ffffff" ContainImg="2" ContainP="0" ContainTable="false" DOMCldNum="3" DoC="7" FontSize="20" FontWeight="normal" FrameSourceIndex="0" ID="1-1" IsImg="false" LinkTextLen="71" ObjectRectHeight="159" ObjectRectLeft="0" ObjectRectTop="0" ObjectRectWidth="1200" SourceIndex="118" TextLen="93" order="2">
<LayoutNode BgColor="#ffffff" ContainImg="2" ContainP="0" ContainTable="false" DOMCldNum="3" DoC="7" FontSize="20" FontWeight="normal" FrameSourceIndex="0" ID="1-1-1" IsImg="false" LinkTextLen="14" ObjectRectHeight="67" ObjectRectLeft="0" ObjectRectTop="0" ObjectRectWidth="1200" SourceIndex="118" TextLen="32" order="3">
<LayoutNode BgColor="#ffffff" ContainImg="2" ContainP="0" ContainTable="false" Content=" Shopping Campaigns " DOMCldNum="3" DoC="8" FontSize="20" FontWeight="normal" FrameSourceIndex="0" ID="1-1-1-1" IsImg="false" LinkTextLen="0" ObjectRectHeight="67" ObjectRectLeft="0" ObjectRectTop="0" ObjectRectWidth="302" SRC="&lt;img alt=&quot;Google&quot; src=&quot;https://www.google.com/images/branding/googlelogo/1x/googlelogo_color_116x41dp.png&quot; srcset=&quot;https://www.google.com/images/branding/googlelogo/2x/googlelogo_color_116x41dp.png 2x&quot;/&gt;&lt;span class=&quot;site-name&quot;&gt;Shopping Campaigns&lt;/span&gt;" SourceIndex="963;121" TextLen="18" order="4"/>
<LayoutNode BgColor="#ffffff" ContainImg="0" ContainP="0" ContainTable="false" DOMCldNum="5" DoC="8" FontSize="14" FontWeight="normal" FrameSourceIndex="0" ID="1-1-1-2" IsImg="false" LinkTextLen="14" ObjectRectHeight="67" ObjectRectLeft="1004" ObjectRectTop="0" ObjectRectWidth="196" SourceIndex="166" TextLen="14" order="5">
<LayoutNode BgColor="#ffffff" ContainImg="0" ContainP="0" ContainTable="false" Content="SIGN IN " DOMCldNum="5" DoC="10" FontSize="14" FontWeight="normal" FrameSourceIndex="0" ID="1-1-1-2-1" IsImg="false" LinkTextLen="7" ObjectRectHeight="67" ObjectRectLeft="1004" ObjectRectTop="0" ObjectRectWidth="68" SRC="&lt;a class=&quot;cta-signin&quot; href=&quot;https://adwords.google.com/um/signin&quot;&gt;Sign in&lt;/a&gt;" SourceIndex="168" TextLen="7" order="6"/>
<LayoutNode BgColor="#00c853" ContainImg="0" ContainP="0" ContainTable="false" Content="SIGN UP " DOMCldNum="5" DoC="10" FontSize="14" FontWeight="normal" FrameSourceIndex="0" ID="1-1-1-2-2" IsImg="false" LinkTextLen="7" ObjectRectHeight="67" ObjectRectLeft="1116" ObjectRectTop="0" ObjectRectWidth="84" SRC="&lt;a class=&quot;cta-signup&quot; href=&quot;../../retail/shopping-campaigns/get-started/&quot;&gt;Sign Up&lt;/a&gt;" SourceIndex="171" TextLen="7" order="7"/>
</LayoutNode>
</LayoutNode>
<LayoutNode BgColor="#ffffff" ContainImg="0" ContainP="0" ContainTable="false" DOMCldNum="13" DoC="8" FontSize="14" FontWeight="normal" FrameSourceIndex="0" ID="1-1-2" IsImg="false" LinkTextLen="57" ObjectRectHeight="87" ObjectRectLeft="0" ObjectRectTop="72" ObjectRectWidth="1200" SourceIndex="130" TextLen="61" order="8">
<LayoutNode BgColor="#ffffff" ContainImg="0" ContainP="0" ContainTable="false" Content="Home " DOMCldNum="13" DoC="10" FontSize="14" FontWeight="normal" FrameSourceIndex="0" ID="1-1-2-1" IsImg="false" LinkTextLen="0" ObjectRectHeight="87" ObjectRectLeft="0" ObjectRectTop="72" ObjectRectWidth="80" SRC="&lt;li class=&quot;active&quot;&gt;Home&#13;          &lt;/li&gt;" SourceIndex="132" TextLen="4" order="9"/>
<LayoutNode BgColor="#ffffff" ContainImg="0" ContainP="0" ContainTable="false" Content="How It Works " DOMCldNum="3" DoC="10" FontSize="14" FontWeight="normal" FrameSourceIndex="0" ID="1-1-2-2" IsImg="false" LinkTextLen="12" ObjectRectHeight="87" ObjectRectLeft="124" ObjectRectTop="72" ObjectRectWidth="81" SRC="&lt;a href=&quot;../../retail/shopping-campaigns/how-it-works/&quot;&gt;How It Works&lt;/a&gt;" SourceIndex="137" TextLen="12" order="10"/>
<LayoutNode BgColor="#ffffff" ContainImg="0" ContainP="0" ContainTable="false" Content="Ad Options " DOMCldNum="3" DoC="10" FontSize="14" FontWeight="normal" FrameSourceIndex="0" ID="1-1-2-3" IsImg="false" LinkTextLen="10" ObjectRectHeight="87" ObjectRectLeft="249" ObjectRectTop="72" ObjectRectWidth="70" SRC="&lt;a href=&quot;../../retail/shopping-campaigns/all-ad-options/&quot;&gt;Ad Options&lt;/a&gt;" SourceIndex="143" TextLen="10" order="11"/>
<LayoutNode BgColor="#ffffff" ContainImg="0" ContainP="0" ContainTable="false" Content="Success Stories " DOMCldNum="3" DoC="10" FontSize="14" FontWeight="normal" FrameSourceIndex="0" ID="1-1-2-4" IsImg="false" LinkTextLen="15" ObjectRectHeight="87" ObjectRectLeft="363" ObjectRectTop="72" ObjectRectWidth="101" SRC="&lt;a href=&quot;../../retail/shopping-campaigns/success-stories/&quot;&gt;Success Stories&lt;/a&gt;" SourceIndex="149" TextLen="15" order="12"/>
<LayoutNode BgColor="#ffffff" ContainImg="0" ContainP="0" ContainTable="false" Content="Resources " DOMCldNum="3" DoC="10" FontSize="14" FontWeight="normal" FrameSourceIndex="0" ID="1-1-2-5" IsImg="false" LinkTextLen="9" ObjectRectHeight="87" ObjectRectLeft="508" ObjectRectTop="72" ObjectRectWidth="68" SRC="&lt;a href=&quot;../../retail/shopping-campaigns/resources/&quot;&gt;Resources&lt;/a&gt;" SourceIndex="155" TextLen="9" order="13"/>
<LayoutNode BgColor="#ffffff" ContainImg="0" ContainP="0" ContainTable="false" Content="Get Started " DOMCldNum="3" DoC="10" FontSize="14" FontWeight="normal" FrameSourceIndex="0" ID="1-1-2-6" IsImg="false" LinkTextLen="11" ObjectRectHeight="87" ObjectRectLeft="620" ObjectRectTop="72" ObjectRectWidth="580" SRC="&lt;a href=&quot;../../retail/shopping-campaigns/get-started/&quot;&gt;Get Started&lt;/a&gt;" SourceIndex="161" TextLen="11" order="14"/>
</LayoutNode>
</LayoutNode>
<LayoutNode BgColor="#ffffff" ContainImg="0" ContainP="0" ContainTable="false" Content="Turn online browsing into online buying. " DOMCldNum="7" DoC="10" FontSize="48" FontWeight="normal" FrameSourceIndex="0" ID="1-2" IsImg="false" LinkTextLen="0" ObjectRectHeight="58" ObjectRectLeft="0" ObjectRectTop="239" ObjectRectWidth="1200" SRC="&lt;h1&gt;&#13;                Turn online browsing into online buying.&#13;              &lt;/h1&gt;" SourceIndex="194" TextLen="40" order="15"/>
<LayoutNode BgColor="#ffffff" ContainImg="0" ContainP="1" ContainTable="false" Content="With Google Shopping campaigns, you reach the shoppers who matter most — the ones searching for what you sell. " DOMCldNum="7" DoC="10" FontSize="18" FontWeight="normal" FrameSourceIndex="0" ID="1-3" IsImg="false" LinkTextLen="0" ObjectRectHeight="24" ObjectRectLeft="0" ObjectRectTop="322" ObjectRectWidth="1200" SRC="&lt;p class=&quot;font-large&quot;&gt;&#13;                With Google Shopping campaigns, you reach the shoppers who matter most — the ones&#13;                searching for what you sell.&#13;              &lt;/p&gt;" SourceIndex="197" TextLen="110" order="16"/>
<LayoutNode BgColor="#00c853" ContainImg="2" ContainP="1" ContainTable="false" DOMCldNum="3" DoC="8" FontSize="16" FontWeight="normal" FrameSourceIndex="0" ID="1-4" IsImg="false" LinkTextLen="9" ObjectRectHeight="178" ObjectRectLeft="0" ObjectRectTop="371" ObjectRectWidth="1200" SourceIndex="202" TextLen="79" order="17">
<LayoutNode BgColor="#00c853" ContainImg="0" ContainP="0" ContainTable="false" Content="START NOW " DOMCldNum="3" DoC="10" FontSize="16" FontWeight="normal" FrameSourceIndex="0" ID="1-4-1" IsImg="false" LinkTextLen="9" ObjectRectHeight="48" ObjectRectLeft="0" ObjectRectTop="371" ObjectRectWidth="1200" SRC="&lt;a class=&quot;button cta-main&quot; href=&quot;../../retail/shopping-campaigns/get-started/&quot;&gt;Start Now&lt;/a&gt;" SourceIndex="1048" TextLen="9" order="18"/>
<LayoutNode BgColor="#ffffff" ContainImg="2" ContainP="1" ContainTable="false" DOMCldNum="7" DoC="8" FontSize="16" FontWeight="normal" FrameSourceIndex="0" ID="1-4-2" IsImg="false" LinkTextLen="0" ObjectRectHeight="110" ObjectRectLeft="0" ObjectRectTop="439" ObjectRectWidth="1200" SourceIndex="208" TextLen="70" order="19">
<LayoutNode BgColor="#ffffff" ContainImg="0" ContainP="1" ContainTable="false" Content="Talk to a human. " DOMCldNum="7" DoC="10" FontSize="16" FontWeight="normal" FrameSourceIndex="0" ID="1-4-2-1" IsImg="false" LinkTextLen="0" ObjectRectHeight="22" ObjectRectLeft="0" ObjectRectTop="439" ObjectRectWidth="1200" SRC="&lt;p class=&quot;talk-to-human&quot;&gt;&#13;                    Talk to a human.&#13;                  &lt;/p&gt;" SourceIndex="210" TextLen="16" order="20"/>
<LayoutNode BgColor="#ffffff" ContainImg="2" ContainP="0" ContainTable="false" Content="  1-866-246-6453 " DOMCldNum="4" DoC="8" FontSize="16" FontWeight="normal" FrameSourceIndex="0" ID="1-4-2-2" IsImg="false" LinkTextLen="0" ObjectRectHeight="24" ObjectRectLeft="0" ObjectRectTop="468" ObjectRectWidth="1200" SRC="&lt;img alt=&quot;phone icon&quot; class=&quot;icon-phone-green&quot; height=&quot;16&quot; src=&quot;//www.google.com/ads/images/icons/icon-ui-phone.png&quot; width=&quot;16&quot;/&gt; 1-866-246-6453" SourceIndex="1065;0" TextLen="15" order="21"/>
<LayoutNode BgColor="#ffffff" ContainImg="0" ContainP="0" ContainTable="false" Content="Free phone support (Mon–Fri, 9am–8pm ET) " DOMCldNum="3" DoC="10" FontSize="12" FontWeight="normal" FrameSourceIndex="0" ID="1-4-2-3" IsImg="false" LinkTextLen="0" ObjectRectHeight="32" ObjectRectLeft="0" ObjectRectTop="517" ObjectRectWidth="1200" SRC="Free phone support(Mon–Fri, 9am–8pm ET)" SourceIndex="0;0" TextLen="39" order="22"/>
</LayoutNode>
</LayoutNode>
<LayoutNode BgColor="#ffffff" ContainImg="0" ContainP="1" ContainTable="false" DOMCldNum="1" DoC="7" FontSize="16" FontWeight="normal" FrameSourceIndex="0" ID="1-5" IsImg="false" LinkTextLen="16" ObjectRectHeight="245" ObjectRectLeft="0" ObjectRectTop="1117" ObjectRectWidth="1200" SourceIndex="261" TextLen="239" order="23">
<LayoutNode BgColor="#ffffff" ContainImg="0" ContainP="0" ContainTable="false" Content="HOW IT WORKS " DOMCldNum="1" DoC="10" FontSize="16" FontWeight="normal" FrameSourceIndex="0" ID="1-5-1" IsImg="false" LinkTextLen="0" ObjectRectHeight="22" ObjectRectLeft="0" ObjectRectTop="1117" ObjectRectWidth="1200" SRC="HOW IT WORKS" SourceIndex="0" TextLen="12" order="24"/>
<LayoutNode BgColor="#ffffff" ContainImg="0" ContainP="0" ContainTable="false" Content="Get on Google, get results. " DOMCldNum="8" DoC="10" FontSize="38" FontWeight="normal" FrameSourceIndex="0" ID="1-5-2" IsImg="false" LinkTextLen="0" ObjectRectHeight="48" ObjectRectLeft="0" ObjectRectTop="1194" ObjectRectWidth="1200" SRC="&lt;h2&gt;&#13;                Get on Google, get results.&#13;              &lt;/h2&gt;" SourceIndex="264" TextLen="27" order="25"/>
<LayoutNode BgColor="#ffffff" ContainImg="0" ContainP="1" ContainTable="false" Content="Get in front of people searching for products you sell, whether they’re shopping at home or on the go. Only pay whenshoppers click through to your website or view your local inventory. " DOMCldNum="8" DoC="10" FontSize="18" FontWeight="normal" FrameSourceIndex="0" ID="1-5-3" IsImg="false" LinkTextLen="0" ObjectRectHeight="48" ObjectRectLeft="0" ObjectRectTop="1267" ObjectRectWidth="1200" SRC="&lt;p class=&quot;font-large&quot;&gt;&#13;                Get in front of people searching for products you sell, whether they’re shopping at&#13;                home or on the go. Only pay when shoppers click through to your website or view&#13;                your local inventory.&#13;              &lt;/p&gt;" SourceIndex="267" TextLen="184" order="26"/>
<LayoutNode BgColor="#ffffff" ContainImg="0" ContainP="0" ContainTable="false" Content="SEE HOW IT WORKS " DOMCldNum="0" DoC="10" FontSize="16" FontWeight="normal" FrameSourceIndex="0" ID="1-5-4" IsImg="false" LinkTextLen="16" ObjectRectHeight="22" ObjectRectLeft="0" ObjectRectTop="1340" ObjectRectWidth="1200" SRC="&lt;a class=&quot;link-more&quot; href=&quot;../../retail/shopping-campaigns/how-it-works/&quot;&gt;See how&#13;              it works &lt;svg xmlns=&quot;http://www.w3.org/2000/svg&quot; xmlns:xlink=&quot;http://www.w3.org/1999/xlink&quot; class=&quot;icon-arrow-more&quot; enable-background=&quot;new 0 0 32 32&quot; height=&quot;14px&quot; version=&quot;1.1&quot; viewbox=&quot;0 0 32 32&quot; width=&quot;14px&quot; x=&quot;0px&quot; xml:space=&quot;preserve&quot; y=&quot;0px&quot;&gt;&#13;              &lt;path d=&quot;M16,0C7.2,0,0,7.2,0,16s7.2,16,16,16c8.8,0,16-7.2,16-16S24.8,0,16,0 M16,25.7L14.3,24l6.8-6.8H7v-2.4h14.1L14.3,8L16,6.3 l9.7,9.7L16,25.7z&quot;&gt;&#13;              &lt;/path&gt;&lt;/svg&gt;&lt;/a&gt;" SourceIndex="269" TextLen="16" order="27"/>
</LayoutNode>
<LayoutNode BgColor="#ffffff" ContainImg="2" ContainP="1" ContainTable="false" DOMCldNum="1" DoC="7" FontSize="16" FontWeight="normal" FrameSourceIndex="0" ID="1-6" IsImg="false" LinkTextLen="22" ObjectRectHeight="1205" ObjectRectLeft="0" ObjectRectTop="1851" ObjectRectWidth="1200" SourceIndex="377" TextLen="147" order="28">
<LayoutNode BgColor="#ffffff" ContainImg="0" ContainP="0" ContainTable="false" Content="AD OPTIONS " DOMCldNum="1" DoC="10" FontSize="16" FontWeight="normal" FrameSourceIndex="0" ID="1-6-1" IsImg="false" LinkTextLen="0" ObjectRectHeight="22" ObjectRectLeft="0" ObjectRectTop="1851" ObjectRectWidth="1200" SRC="AD OPTIONS" SourceIndex="0" TextLen="10" order="29"/>
<LayoutNode BgColor="#ffffff" ContainImg="0" ContainP="0" ContainTable="false" Content="Encourage clicky behavior. " DOMCldNum="8" DoC="8" FontSize="38" FontWeight="normal" FrameSourceIndex="0" ID="1-6-2" IsImg="false" LinkTextLen="0" ObjectRectHeight="48" ObjectRectLeft="0" ObjectRectTop="1928" ObjectRectWidth="1200" SRC="&lt;h2&gt;&#13;                Encourage &lt;span class=&quot;text-nowrap&quot;&gt;clicky&lt;/span&gt; behavior.&#13;              &lt;/h2&gt;" SourceIndex="380" TextLen="26" order="30"/>
<LayoutNode BgColor="#ffffff" ContainImg="0" ContainP="1" ContainTable="false" Content="Spark shoppers’ interest with special offers, reviews and ratings — and a whole lot more. " DOMCldNum="8" DoC="10" FontSize="18" FontWeight="normal" FrameSourceIndex="0" ID="1-6-3" IsImg="false" LinkTextLen="0" ObjectRectHeight="24" ObjectRectLeft="0" ObjectRectTop="2001" ObjectRectWidth="1200" SRC="&lt;p class=&quot;font-large&quot;&gt;&#13;                Spark shoppers’ interest with special offers, reviews and ratings — and a whole lot&#13;                more.&#13;              &lt;/p&gt;" SourceIndex="386" TextLen="89" order="31"/>
<LayoutNode BgColor="#ffffff" ContainImg="2" ContainP="0" ContainTable="false" Content="EXPLORE ALL AD OPTIONS  " DOMCldNum="0" DoC="10" FontSize="16" FontWeight="normal" FrameSourceIndex="0" ID="1-6-4" IsImg="false" LinkTextLen="22" ObjectRectHeight="1006" ObjectRectLeft="0" ObjectRectTop="2050" ObjectRectWidth="1200" SRC="&lt;a class=&quot;link-more&quot; href=&quot;../../retail/shopping-campaigns/all-ad-options/&quot;&gt;Explore all ad options &lt;svg xmlns=&quot;http://www.w3.org/2000/svg&quot; xmlns:xlink=&quot;http://www.w3.org/1999/xlink&quot; class=&quot;icon-arrow-more&quot; enable-background=&quot;new 0 0 32 32&quot; height=&quot;14px&quot; version=&quot;1.1&quot; viewbox=&quot;0 0 32 32&quot; width=&quot;14px&quot; x=&quot;0px&quot; xml:space=&quot;preserve&quot; y=&quot;0px&quot;&gt;&#13;              &lt;path d=&quot;M16,0C7.2,0,0,7.2,0,16s7.2,16,16,16c8.8,0,16-7.2,16-16S24.8,0,16,0 M16,25.7L14.3,24l6.8-6.8H7v-2.4h14.1L14.3,8L16,6.3 l9.7,9.7L16,25.7z&quot;&gt;&#13;              &lt;/path&gt;&lt;/svg&gt;&lt;/a&gt;&lt;img alt=&quot;&quot; srcset=&quot;../../retail/images/shopping-campaigns/ad-options_m_1x.png?mmfb=7bb8c2a815e6ad0a3fc6388e431a48fa, ../../retail/images/shopping-campaigns/ad-options_m_2x.png?mmfb=1b05832314cfd8b4b60a3ecf7310f316 2x&quot;/&gt;" SourceIndex="388;1247" TextLen="22" order="32"/>
</LayoutNode>
<LayoutNode BgColor="#ffffff" ContainImg="2" ContainP="1" ContainTable="false" DOMCldNum="1" DoC="7" FontSize="16" FontWeight="normal" FrameSourceIndex="0" ID="1-7" IsImg="false" LinkTextLen="0" ObjectRectHeight="651" ObjectRectLeft="0" ObjectRectTop="3238" ObjectRectWidth="1200" SourceIndex="424" TextLen="156" order="33">
<LayoutNode BgColor="#ffffff" ContainImg="0" ContainP="0" ContainTable="false" Content="TRACK PERFORMANCE " DOMCldNum="1" DoC="10" FontSize="16" FontWeight="normal" FrameSourceIndex="0" ID="1-7-1" IsImg="false" LinkTextLen="0" ObjectRectHeight="22" ObjectRectLeft="0" ObjectRectTop="3238" ObjectRectWidth="1200" SRC="TRACK PERFORMANCE" SourceIndex="0" TextLen="17" order="34"/>
<LayoutNode BgColor="#ffffff" ContainImg="0" ContainP="0" ContainTable="false" Content="See what’s working. Fix what’s not. " DOMCldNum="7" DoC="10" FontSize="38" FontWeight="normal" FrameSourceIndex="0" ID="1-7-2" IsImg="false" LinkTextLen="0" ObjectRectHeight="48" ObjectRectLeft="0" ObjectRectTop="3315" ObjectRectWidth="1200" SRC="&lt;h2&gt;&#13;                See what’s working. Fix what’s not.&#13;              &lt;/h2&gt;" SourceIndex="427" TextLen="35" order="35"/>
<LayoutNode BgColor="#ffffff" ContainImg="2" ContainP="1" ContainTable="false" Content="Our tools and detailed reports can tell you what’s working, what isn’t, and how to improve your results.  " DOMCldNum="7" DoC="10" FontSize="18" FontWeight="normal" FrameSourceIndex="0" ID="1-7-3" IsImg="false" LinkTextLen="0" ObjectRectHeight="501" ObjectRectLeft="0" ObjectRectTop="3388" ObjectRectWidth="1200" SRC="&lt;p class=&quot;font-large&quot; data-rs-trigger=&quot;laptopAnimate&quot;&gt;&#13;                Our tools and detailed reports can tell you what’s working, what isn’t, and how to&#13;                improve your results.&#13;              &lt;/p&gt;&lt;img alt=&quot;&quot; srcset=&quot;../../retail/images/shopping-campaigns/adwords_m_1x.png, ../../retail/images/shopping-campaigns/adwords_m_2x.png 2x&quot;/&gt;" SourceIndex="430;1285" TextLen="104" order="36"/>
</LayoutNode>
<LayoutNode BgColor="#ffffff" ContainImg="0" ContainP="0" ContainTable="false" Content="More solutions for your business. " DOMCldNum="7" DoC="10" FontSize="38" FontWeight="normal" FrameSourceIndex="0" ID="1-8" IsImg="false" LinkTextLen="0" ObjectRectHeight="48" ObjectRectLeft="0" ObjectRectTop="4077" ObjectRectWidth="1200" SRC="&lt;h2&gt;&#13;            More solutions for your business.&#13;          &lt;/h2&gt;" SourceIndex="453" TextLen="33" order="37"/>
<LayoutNode BgColor="#ffffff" ContainImg="4" ContainP="1" ContainTable="false" DOMCldNum="8" DoC="8" FontSize="14" FontWeight="normal" FrameSourceIndex="0" ID="1-9" IsImg="false" LinkTextLen="0" ObjectRectHeight="280" ObjectRectLeft="0" ObjectRectTop="4180" ObjectRectWidth="1200" SourceIndex="460" TextLen="137" order="38">
<LayoutNode BgColor="#ffffff" ContainImg="2" ContainP="0" ContainTable="false" Content=" " DOMCldNum="8" DoC="11" FontSize="14" FontWeight="normal" FrameSourceIndex="0" ID="1-9-1" IsImg="true" LinkTextLen="0" ObjectRectHeight="64" ObjectRectLeft="0" ObjectRectTop="4180" ObjectRectWidth="1200" SRC="&lt;img alt=&quot;&quot; class=&quot;product-logo&quot; src=&quot;https://www.google.com/ads/images/icons/icon-product-googlecustomerreview-64.png&quot;/&gt;" SourceIndex="1305" TextLen="0" order="39"/>
<LayoutNode BgColor="#ffffff" ContainImg="0" ContainP="0" ContainTable="false" Content="Google CustomerReviews " DOMCldNum="8" DoC="10" FontSize="22" FontWeight="normal" FrameSourceIndex="0" ID="1-9-2" IsImg="false" LinkTextLen="0" ObjectRectHeight="60" ObjectRectLeft="0" ObjectRectTop="4279" ObjectRectWidth="1200" SRC="&lt;h3&gt;&#13;                Google Customer Reviews&#13;              &lt;/h3&gt;" SourceIndex="463" TextLen="22" order="40"/>
<LayoutNode BgColor="#ffffff" ContainImg="2" ContainP="1" ContainTable="false" Content="Collect valuable customer reviewsand earn seller ratings that will showup on your search ads and onGoogle Shopping.  " DOMCldNum="8" DoC="8" FontSize="14" FontWeight="normal" FrameSourceIndex="0" ID="1-9-3" IsImg="false" LinkTextLen="0" ObjectRectHeight="107" ObjectRectLeft="0" ObjectRectTop="4353" ObjectRectWidth="1200" SRC="&lt;p class=&quot;last&quot;&gt;&#13;                Collect valuable customer reviews and earn seller ratings that will show up on your&#13;                search ads and on Google Shopping.&#13;              &lt;/p&gt;&lt;img alt=&quot;related arrow icon&quot; class=&quot;icon-arrow-related&quot; height=&quot;16&quot; src=&quot;//www.google.com/ads/images/icons/icon-arrow-related.png&quot; width=&quot;16&quot;/&gt;" SourceIndex="466;1317" TextLen="115" order="41"/>
</LayoutNode>
<LayoutNode BgColor="#ffffff" ContainImg="4" ContainP="1" ContainTable="false" DOMCldNum="8" DoC="8" FontSize="14" FontWeight="normal" FrameSourceIndex="0" ID="1-10" IsImg="false" LinkTextLen="0" ObjectRectHeight="280" ObjectRectLeft="0" ObjectRectTop="4585" ObjectRectWidth="1200" SourceIndex="478" TextLen="97" order="42">
<LayoutNode BgColor="#ffffff" ContainImg="2" ContainP="0" ContainTable="false" Content=" " DOMCldNum="8" DoC="11" FontSize="14" FontWeight="normal" FrameSourceIndex="0" ID="1-10-1" IsImg="true" LinkTextLen="0" ObjectRectHeight="64" ObjectRectLeft="0" ObjectRectTop="4585" ObjectRectWidth="1200" SRC="&lt;img alt=&quot;&quot; class=&quot;product-logo&quot; src=&quot;//www.google.com/ads/images/icons/icon-product-localinventory-64.png&quot;/&gt;" SourceIndex="1323" TextLen="0" order="43"/>
<LayoutNode BgColor="#ffffff" ContainImg="0" ContainP="0" ContainTable="false" Content="Local Inventory Ads " DOMCldNum="8" DoC="10" FontSize="22" FontWeight="normal" FrameSourceIndex="0" ID="1-10-2" IsImg="false" LinkTextLen="0" ObjectRectHeight="30" ObjectRectLeft="0" ObjectRectTop="4684" ObjectRectWidth="1200" SRC="&lt;h3&gt;&#13;                Local Inventory Ads&#13;              &lt;/h3&gt;" SourceIndex="481" TextLen="19" order="44"/>
<LayoutNode BgColor="#ffffff" ContainImg="2" ContainP="1" ContainTable="false" Content="Promote your local inventory onGoogle and entice shoppers to visityour stores.  " DOMCldNum="8" DoC="8" FontSize="14" FontWeight="normal" FrameSourceIndex="0" ID="1-10-3" IsImg="false" LinkTextLen="0" ObjectRectHeight="137" ObjectRectLeft="0" ObjectRectTop="4728" ObjectRectWidth="1200" SRC="&lt;p class=&quot;last&quot;&gt;&#13;                Promote your local inventory on Google and entice shoppers to visit your stores.&#13;              &lt;/p&gt;&lt;img alt=&quot;related arrow icon&quot; class=&quot;icon-arrow-related&quot; height=&quot;16&quot; src=&quot;//www.google.com/ads/images/icons/icon-arrow-related.png&quot; width=&quot;16&quot;/&gt;" SourceIndex="484;1335" TextLen="78" order="45"/>
</LayoutNode>
<LayoutNode BgColor="#ffffff" ContainImg="0" ContainP="0" ContainTable="false" Content="SEE ALL SOLUTIONS " DOMCldNum="3" DoC="10" FontSize="16" FontWeight="normal" FrameSourceIndex="0" ID="1-11" IsImg="false" LinkTextLen="17" ObjectRectHeight="22" ObjectRectLeft="0" ObjectRectTop="4960" ObjectRectWidth="1200" SRC="&lt;a class=&quot;link-more&quot; href=&quot;../../retail/&quot;&gt;See all solutions &lt;svg xmlns=&quot;http://www.w3.org/2000/svg&quot; xmlns:xlink=&quot;http://www.w3.org/1999/xlink&quot; class=&quot;icon-arrow-more&quot; enable-background=&quot;new 0 0 32 32&quot; height=&quot;14px&quot; version=&quot;1.1&quot; viewbox=&quot;0 0 32 32&quot; width=&quot;14px&quot; x=&quot;0px&quot; xml:space=&quot;preserve&quot; y=&quot;0px&quot;&gt;&#13;            &lt;path d=&quot;M16,0C7.2,0,0,7.2,0,16s7.2,16,16,16c8.8,0,16-7.2,16-16S24.8,0,16,0 M16,25.7L14.3,24l6.8-6.8H7v-2.4h14.1L14.3,8L16,6.3 l9.7,9.7L16,25.7z&quot;&gt;&#13;            &lt;/path&gt;&lt;/svg&gt;&lt;/a&gt;" SourceIndex="497" TextLen="17" order="46"/>
<LayoutNode BgColor="#ffffff" ContainImg="4" ContainP="0" ContainTable="false" DOMCldNum="7" DoC="8" FontSize="14" FontWeight="normal" FrameSourceIndex="0" ID="1-12" IsImg="false" LinkTextLen="0" ObjectRectHeight="22" ObjectRectLeft="0" ObjectRectTop="5076" ObjectRectWidth="1200" SourceIndex="516" TextLen="13" order="47">
<LayoutNode BgColor="#ffffff" ContainImg="0" ContainP="0" ContainTable="false" Content="Follow us on: " DOMCldNum="7" DoC="10" FontSize="14" FontWeight="normal" FrameSourceIndex="0" ID="1-12-1" IsImg="false" LinkTextLen="0" ObjectRectHeight="22" ObjectRectLeft="0" ObjectRectTop="5076" ObjectRectWidth="199" SRC="&lt;dt&gt;&#13;                Follow us on:&#13;              &lt;/dt&gt;" SourceIndex="518" TextLen="13" order="48"/>
<LayoutNode BgColor="#ffffff" ContainImg="2" ContainP="0" ContainTable="false" Content=" " DOMCldNum="3" DoC="8" FontSize="14" FontWeight="normal" FrameSourceIndex="0" ID="1-12-2" IsImg="true" LinkTextLen="0" ObjectRectHeight="22" ObjectRectLeft="225" ObjectRectTop="5076" ObjectRectWidth="20" SRC="&lt;img alt=&quot;Google+&quot; class=&quot;icon-footer-gplus&quot; height=&quot;20&quot; src=&quot;//www.google.com/ads/images/icons/icon-footer-gplus.png&quot; width=&quot;20&quot;/&gt;" SourceIndex="1376" TextLen="0" order="49"/>
<LayoutNode BgColor="#ffffff" ContainImg="2" ContainP="0" ContainTable="false" Content=" " DOMCldNum="3" DoC="8" FontSize="14" FontWeight="normal" FrameSourceIndex="0" ID="1-12-3" IsImg="true" LinkTextLen="0" ObjectRectHeight="22" ObjectRectLeft="271" ObjectRectTop="5076" ObjectRectWidth="929" SRC="&lt;img alt=&quot;Blogger&quot; class=&quot;icon-footer-blogger&quot; height=&quot;20&quot; src=&quot;//www.google.com/ads/images/icons/icon-footer-blogger.png&quot; width=&quot;20&quot;/&gt;" SourceIndex="1387" TextLen="0" order="50"/>
</LayoutNode>
<LayoutNode BgColor="#ffffff" ContainImg="0" ContainP="0" ContainTable="false" Content="Learning &amp; Support Merchant Center Help Manufacturer Center Help AdWords Help Center Google Small Business Community Developers Google Developers Site Content API for Shopping Related Products Merchant Center Manufacturer Center AdSense for Shopping AdWords More Solutions from Google Business Solutions Google for Retail Google Apps for Work Google Analytics Think with Google " DOMCldNum="11" DoC="9" FontSize="18" FontWeight="normal" FrameSourceIndex="0" ID="1-13" IsImg="false" LinkTextLen="289" ObjectRectHeight="608" ObjectRectLeft="0" ObjectRectTop="5133" ObjectRectWidth="1200" SRC="&lt;dt&gt;&#13;              Learning &amp;amp; Support&#13;            &lt;/dt&gt;&lt;a href=&quot;https://support.google.com/merchants/?hl=en#topic=3404821&quot; target=&quot;_blank&quot;&gt;Merchant Center Help&lt;/a&gt;&lt;a href=&quot;https://support.google.com/manufacturers/#topic=6124028/?hl=en&quot; target=&quot;_blank&quot;&gt;Manufacturer Center Help&lt;/a&gt;&lt;a href=&quot;https://support.google.com/adwords/#topic=3119071?hl=en&quot; target=&quot;_blank&quot;&gt;AdWords Help Center&lt;/a&gt;&lt;a href=&quot;https://www.en.advertisercommunity.com/t5/Google-Small-Business/ct-p/Google_Small_Business&quot; rel=&quot;nofollow&quot; target=&quot;_blank&quot;&gt;Google Small Business Community&lt;/a&gt;&lt;dt&gt;&#13;              Developers&#13;            &lt;/dt&gt;&lt;a href=&quot;https://developers.google.com/?hl=en&quot; target=&quot;_blank&quot;&gt;Google Developers&#13;              Site&lt;/a&gt;&lt;a href=&quot;https://developers.google.com/shopping-content/v2/quickstart?hl=en&quot; target=&quot;_blank&quot;&gt;Content API for Shopping&lt;/a&gt;&lt;dt&gt;&#13;              Related Products&#13;            &lt;/dt&gt;&lt;a href=&quot;https://www.google.com/retail/solutions/merchant-center/&quot; target=&quot;_blank&quot;&gt;Merchant Center&lt;/a&gt;&lt;a href=&quot;https://www.google.com/retail/solutions/manufacturer-center/&quot; target=&quot;_blank&quot;&gt;Manufacturer Center&lt;/a&gt;&lt;a href=&quot;https://support.google.com/adsense/answer/6078274?hl=en&quot; target=&quot;_blank&quot;&gt;AdSense for Shopping&lt;/a&gt;&lt;a href=&quot;https://www.google.com/adwords/?sourceid=awo&amp;amp;subid=us-en-et-retail-rsftr&quot; target=&quot;_blank&quot;&gt;AdWords&lt;/a&gt;&lt;dt&gt;&#13;              More Solutions from Google&#13;            &lt;/dt&gt;&lt;a href=&quot;https://www.google.com/services/&quot; target=&quot;_blank&quot;&gt;Business Solutions&lt;/a&gt;&lt;a href=&quot;https://www.google.com/retail/&quot; target=&quot;_blank&quot;&gt;Google for Retail&lt;/a&gt;&lt;a href=&quot;https://gsuite.google.com/intl/en/&quot; target=&quot;_blank&quot;&gt;Google Apps for Work&lt;/a&gt;&lt;a href=&quot;https://www.google.com/analytics/&quot; target=&quot;_blank&quot;&gt;Google Analytics&lt;/a&gt;&lt;a href=&quot;https://www.thinkwithgoogle.com/marketing-resources/local-retail-playbook/&quot; target=&quot;_blank&quot;&gt;Think with Google&lt;/a&gt;" SourceIndex="551" TextLen="359" order="51"/>
<LayoutNode BgColor="#ffffff" ContainImg="2" ContainP="0" ContainTable="false" DOMCldNum="4" DoC="8" FontSize="14" FontWeight="normal" FrameSourceIndex="0" ID="1-14" IsImg="false" LinkTextLen="18" ObjectRectHeight="81" ObjectRectLeft="0" ObjectRectTop="5771" ObjectRectWidth="1200" SourceIndex="674" TextLen="23" order="52">
<LayoutNode BgColor="#ffffff" ContainImg="2" ContainP="0" ContainTable="false" Content=" " DOMCldNum="4" DoC="8" FontSize="14" FontWeight="normal" FrameSourceIndex="0" ID="1-14-1" IsImg="true" LinkTextLen="0" ObjectRectHeight="81" ObjectRectLeft="0" ObjectRectTop="5771" ObjectRectWidth="128" SRC="&lt;img alt=&quot;Help&quot; class=&quot;icon-footer-help&quot; height=&quot;20&quot; src=&quot;//www.google.com/ads/images/icons/icon-footer-help.png&quot; width=&quot;20&quot;/&gt;" SourceIndex="1523" TextLen="0" order="53"/>
<LayoutNode BgColor="#ffffff" ContainImg="0" ContainP="0" ContainTable="false" Content=" Help " DOMCldNum="4" DoC="10" FontSize="14" FontWeight="normal" FrameSourceIndex="0" ID="1-14-2" IsImg="false" LinkTextLen="0" ObjectRectHeight="81" ObjectRectLeft="138" ObjectRectTop="5771" ObjectRectWidth="32" SRC=" Help" SourceIndex="0" TextLen="5" order="54"/>
<LayoutNode BgColor="#ffffff" ContainImg="0" ContainP="0" ContainTable="false" Content="Google " DOMCldNum="3" DoC="10" FontSize="14" FontWeight="normal" FrameSourceIndex="0" ID="1-14-3" IsImg="false" LinkTextLen="6" ObjectRectHeight="81" ObjectRectLeft="198" ObjectRectTop="5771" ObjectRectWidth="46" SRC="&lt;a href=&quot;//www.google.com&quot;&gt;Google&lt;/a&gt;" SourceIndex="685" TextLen="6" order="55"/>
<LayoutNode BgColor="#ffffff" ContainImg="0" ContainP="0" ContainTable="false" Content="Privacy " DOMCldNum="3" DoC="10" FontSize="14" FontWeight="normal" FrameSourceIndex="0" ID="1-14-4" IsImg="false" LinkTextLen="7" ObjectRectHeight="81" ObjectRectLeft="272" ObjectRectTop="5771" ObjectRectWidth="46" SRC="&lt;a href=&quot;//www.google.com/intl/en/policies/privacy/&quot;&gt;Privacy&lt;/a&gt;" SourceIndex="691" TextLen="7" order="56"/>
<LayoutNode BgColor="#ffffff" ContainImg="0" ContainP="0" ContainTable="false" Content="Terms " DOMCldNum="3" DoC="10" FontSize="14" FontWeight="normal" FrameSourceIndex="0" ID="1-14-5" IsImg="false" LinkTextLen="5" ObjectRectHeight="81" ObjectRectLeft="346" ObjectRectTop="5771" ObjectRectWidth="854" SRC="&lt;a href=&quot;//www.google.com/intl/en/policies/terms/&quot;&gt;Terms&lt;/a&gt;" SourceIndex="697" TextLen="5" order="57"/>
</LayoutNode>
</LayoutNode>
</VIPSPage>
